CHANGES.rst
LICENSE
MANIFEST.in
README.rst
setup.py
django_jux.egg-info/PKG-INFO
django_jux.egg-info/SOURCES.txt
django_jux.egg-info/dependency_links.txt
django_jux.egg-info/requires.txt
django_jux.egg-info/top_level.txt
juxd/__init__.py