Metadata-Version: 1.0
Name: django-jux
Version: 1.0.2
Summary: JUnit-style XML output for Django tests
Home-page: https://bitbucket.org/seandst/django-jux
Author: Sean Myers
Author-email: sean.dst@gmail.com
License: MIT Expat License
Platform: UNKNOWN
Classifier: Development Status :: 5 - Production/Stable
Classifier: Framework :: Django
Classifier: Intended Audience :: Developers
Classifier: License :: DFSG approved
Classifier: License :: Freely Distributable
Classifier: License :: OSI Approved :: MIT License
Classifier: Operating System :: OS Independent
Classifier: Programming Language :: Python
Classifier: Topic :: Software Development :: Build Tools
Classifier: Topic :: Software Development :: Testing
